LICENSE
README.md
setup.py
.github/workflows/ci.yaml
flake8_numpydtype/__init__.py
flake8_numpydtype/__main__.py
flake8_numpydtype/checker.py
flake8_numpydtype/version.py
flake8_numpydtype.egg-info/PKG-INFO
flake8_numpydtype.egg-info/SOURCES.txt
flake8_numpydtype.egg-info/dependency_links.txt
flake8_numpydtype.egg-info/entry_points.txt
flake8_numpydtype.egg-info/not-zip-safe
flake8_numpydtype.egg-info/requires.txt
flake8_numpydtype.egg-info/top_level.txt
test/test_flake8.py