Metadata-Version: 2.1
Name: flake8-numpydtype
Version: 0.0.1.0
Summary: flake8 plugin to warn deprecated numpy dtype
Home-page: https://github.com/cielavenir/flake8_numpydtype
Author: cielavenir
Author-email: cielartisan@gmail.com
License: 0BSD
Keywords: flake8
Platform: any
Classifier: Development Status :: 4 - Beta
Classifier: Intended Audience :: Developers
Classifier: License :: Public Domain
Classifier: Operating System :: POSIX
Classifier: Operating System :: Microsoft :: Windows
Classifier: Operating System :: MacOS :: MacOS X
Classifier: Topic :: Software Development :: Libraries
Classifier: Topic :: Utilities
Classifier: Programming Language :: Python :: 2
Classifier: Programming Language :: Python :: 2.7
Classifier: Programming Language :: Python :: 3
Classifier: Programming Language :: Python :: 3.4
Classifier: Programming Language :: Python :: 3.5
Classifier: Programming Language :: Python :: 3.6
Classifier: Programming Language :: Python :: Implementation :: PyPy
